{"packageUniqueID":"AIUNIV_Robotics_Bachelors_Female_2017","universityCode":"AIUNIV","specialty":"Robotics","levelOfEducation":"Bachelors","sex":"Female","yearOfEducation":"2017","graduates":[{"firstName":"Hayley","lastName":"Reid","middleName":"Cairo","birth":"19/06/92"},{"firstName":"Calista","lastName":"Potts","middleName":"Taylor","birth":"15/06/92"},{"firstName":"Kelsey","lastName":"Fitzgerald","middleName":"Idola","birth":"14/03/90"},{"firstName":"Calvin","lastName":"Massey","middleName":"Suki","birth":"13/03/90"},{"firstName":"Burke","lastName":"Grimes","middleName":"Georgia","birth":"20/03/92"},{"firstName":"Jerome","lastName":"Horton","middleName":"Norman","birth":"15/03/90"},{"firstName":"Ivan","lastName":"Patterson","middleName":"Clarke","birth":"14/02/93"}]}
