{"packageUniqueID":"ARIZONA_Cartography_Masters_Female_2016","universityCode":"ARIZONA","specialty":"Cartography","levelOfEducation":"Masters","sex":"Female","yearOfEducation":"2016","graduates":[{"firstName":"Demetria","lastName":"Pace","middleName":"Lawrence","birth":"02/02/92"},{"firstName":"Jordan","lastName":"Foley","middleName":"Xaviera","birth":"17/01/92"},{"firstName":"Elizabeth","lastName":"Fields","middleName":"Audra","birth":"06/12/90"},{"firstName":"Tarik","lastName":"Arnold","middleName":"Marcia","birth":"15/04/94"},{"firstName":"Jade","lastName":"Hooper","middleName":"Dorothy","birth":"30/12/89"},{"firstName":"Mara","lastName":"Hayes","middleName":"Stephanie","birth":"08/08/90"},{"firstName":"Brandon","lastName":"Foster","middleName":"Tasha","birth":"30/05/89"},{"firstName":"Zelenia","lastName":"Davidson","middleName":"Oscar","birth":"22/12/95"}]}
