{"packageUniqueID":"ASTATE_Software Engineering_Doctorate_Male_2017","universityCode":"ASTATE","specialty":"Software Engineering","levelOfEducation":"Doctorate","sex":"Male","yearOfEducation":"2017","graduates":[{"firstName":"Nadine","lastName":"Pitts","middleName":"Karleigh","birth":"04/01/92"},{"firstName":"Macon","lastName":"Luna","middleName":"Florence","birth":"22/08/90"},{"firstName":"Clark","lastName":"Mcleod","middleName":"Burke","birth":"30/05/91"},{"firstName":"Brenna","lastName":"Maxwell","middleName":"Bruno","birth":"25/12/94"},{"firstName":"Lenore","lastName":"Hawkins","middleName":"Acton","birth":"01/01/90"},{"firstName":"Serina","lastName":"Davis","middleName":"Justina","birth":"14/12/90"},{"firstName":"Leonard","lastName":"Hardy","middleName":"Lance","birth":"13/09/90"},{"firstName":"Noel","lastName":"Holden","middleName":"Serena","birth":"30/07/91"},{"firstName":"Florence","lastName":"Benson","middleName":"Fitzgerald","birth":"03/12/94"},{"firstName":"Kenyon","lastName":"William","middleName":"Basia","birth":"08/06/95"},{"firstName":"Cleo","lastName":"Woodward","middleName":"Bernard","birth":"11/02/95"},{"firstName":"Phoebe","lastName":"Dickson","middleName":"Tamara","birth":"19/06/95"},{"firstName":"Marsden","lastName":"Morrow","middleName":"Colin","birth":"13/11/91"},{"firstName":"Channing","lastName":"Wright","middleName":"Ashely","birth":"26/08/93"},{"firstName":"Vanna","lastName":"Ayers","middleName":"Emery","birth":"20/10/93"},{"firstName":"Scarlett","lastName":"Barnes","middleName":"Margaret","birth":"29/05/92"},{"firstName":"Irene","lastName":"Hatfield","middleName":"Erin","birth":"16/02/92"},{"firstName":"Jael","lastName":"Willis","middleName":"Laurel","birth":"22/07/94"},{"firstName":"Beck","lastName":"Holder","middleName":"Cooper","birth":"08/12/93"},{"firstName":"Quin","lastName":"Richard","middleName":"Tanek","birth":"14/04/92"},{"firstName":"Reuben","lastName":"Burns","middleName":"Julie","birth":"20/08/90"},{"firstName":"Darius","lastName":"Pena","middleName":"Kiara","birth":"07/07/92"},{"firstName":"Chaney","lastName":"Cameron","middleName":"Aurelia","birth":"29/05/93"},{"firstName":"Taylor","lastName":"Perry","middleName":"Steel","birth":"11/12/95"},{"firstName":"Hayley","lastName":"Sellers","middleName":"Kitra","birth":"28/11/95"},{"firstName":"Sheila","lastName":"Robinson","middleName":"Stewart","birth":"02/09/94"},{"firstName":"Melyssa","lastName":"Conrad","middleName":"Vance","birth":"15/12/92"},{"firstName":"Hamish","lastName":"Waller","middleName":"Portia","birth":"09/09/94"},{"firstName":"Ayanna","lastName":"Livingston","middleName":"George","birth":"11/11/95"},{"firstName":"Carissa","lastName":"Wilcox","middleName":"Sylvester","birth":"15/05/94"},{"firstName":"Jane","lastName":"Baldwin","middleName":"Aretha","birth":"22/01/94"},{"firstName":"Castor","lastName":"Gallegos","middleName":"Xavier","birth":"04/01/93"},{"firstName":"Nina","lastName":"Monroe","middleName":"Jerry","birth":"05/03/93"},{"firstName":"Sandra","lastName":"Abbott","middleName":"Nola","birth":"02/07/90"},{"firstName":"Ima","lastName":"Alston","middleName":"Sophia","birth":"12/11/91"},{"firstName":"Harriet","lastName":"Perez","middleName":"Alexa","birth":"29/12/93"},{"firstName":"Kennan","lastName":"Emerson","middleName":"Ariana","birth":"27/11/93"},{"firstName":"Ivan","lastName":"Moss","middleName":"Karen","birth":"05/10/95"},{"firstName":"Amal","lastName":"Cochran","middleName":"Jordan","birth":"14/08/95"},{"firstName":"Odette","lastName":"Lyons","middleName":"Naida","birth":"22/10/95"}]}
