{"packageUniqueID":"ASTATE_Information Technology_Doctorate_Male_2016","universityCode":"ASTATE","specialty":"Information Technology","levelOfEducation":"Doctorate","sex":"Male","yearOfEducation":"2016","graduates":[{"firstName":"Karly","lastName":"Nash","middleName":"Daryl","birth":"09/03/91"},{"firstName":"Martin","lastName":"Carroll","middleName":"Colby","birth":"12/01/94"},{"firstName":"Declan","lastName":"Velasquez","middleName":"Ryan","birth":"11/07/92"},{"firstName":"Madonna","lastName":"Valencia","middleName":"Yuli","birth":"24/10/93"},{"firstName":"Elaine","lastName":"Richmond","middleName":"Timon","birth":"06/06/91"},{"firstName":"Hedley","lastName":"Harding","middleName":"Tana","birth":"20/04/95"},{"firstName":"Rosalyn","lastName":"Hopper","middleName":"Eve","birth":"09/11/90"},{"firstName":"Wayne","lastName":"Buck","middleName":"Mason","birth":"23/02/89"}]}
