{"packageUniqueID":"ASTATE_Science and Technology Studies_Masters_Female_2017","universityCode":"ASTATE","specialty":"Science and Technology Studies","levelOfEducation":"Masters","sex":"Female","yearOfEducation":"2017","graduates":[{"firstName":"Gillian","lastName":"Delgado","middleName":"Thor","birth":"02/09/93"},{"firstName":"Paloma","lastName":"Dominguez","middleName":"Zephania","birth":"11/04/90"},{"firstName":"Hayden","lastName":"Sparks","middleName":"Gwendolyn","birth":"19/12/95"},{"firstName":"Kyra","lastName":"Goodman","middleName":"Grady","birth":"29/05/91"},{"firstName":"Benedict","lastName":"Gilmore","middleName":"Evan","birth":"02/10/94"},{"firstName":"Carter","lastName":"Navarro","middleName":"Allistair","birth":"29/11/92"},{"firstName":"Karly","lastName":"Taylor","middleName":"Andrew","birth":"10/12/90"},{"firstName":"Elizabeth","lastName":"Murray","middleName":"Alana","birth":"04/04/89"},{"firstName":"Shafira","lastName":"Donaldson","middleName":"Paloma","birth":"19/01/90"},{"firstName":"Honorato","lastName":"Mason","middleName":"Berk","birth":"12/01/92"},{"firstName":"Lee","lastName":"Bowman","middleName":"Rylee","birth":"20/10/92"},{"firstName":"Louis","lastName":"Mccarty","middleName":"Darryl","birth":"12/09/93"},{"firstName":"Constance","lastName":"Alston","middleName":"Elizabeth","birth":"10/01/95"},{"firstName":"Inez","lastName":"Hines","middleName":"Kamal","birth":"16/03/89"},{"firstName":"Beatrice","lastName":"Joseph","middleName":"Haviva","birth":"21/07/90"},{"firstName":"Kyle","lastName":"Tran","middleName":"Merrill","birth":"03/09/91"},{"firstName":"William","lastName":"Saunders","middleName":"Noble","birth":"12/08/92"},{"firstName":"Gloria","lastName":"Lindsey","middleName":"Clinton","birth":"14/09/93"},{"firstName":"Jenna","lastName":"Avila","middleName":"Caesar","birth":"18/01/92"},{"firstName":"Helen","lastName":"Carney","middleName":"Grace","birth":"27/11/91"},{"firstName":"Penelope","lastName":"Franks","middleName":"Sage","birth":"16/08/95"},{"firstName":"Lael","lastName":"Carter","middleName":"Mechelle","birth":"18/04/90"},{"firstName":"Sawyer","lastName":"Pitts","middleName":"Leo","birth":"29/09/89"},{"firstName":"Jennifer","lastName":"Morris","middleName":"Tyler","birth":"28/04/90"},{"firstName":"Iliana","lastName":"Norman","middleName":"Derek","birth":"24/06/92"},{"firstName":"Lara","lastName":"Gould","middleName":"Bradley","birth":"16/08/90"},{"firstName":"Maxwell","lastName":"House","middleName":"Florence","birth":"11/10/93"},{"firstName":"Colette","lastName":"Galloway","middleName":"Zelda","birth":"07/03/95"},{"firstName":"Macaulay","lastName":"Dennis","middleName":"Phelan","birth":"25/12/89"},{"firstName":"Christopher","lastName":"Dixon","middleName":"Melvin","birth":"01/03/93"}]}
