{"packageUniqueID":"ATHENS_Science and Technology Studies_Bachelors_Female_2015","universityCode":"ATHENS","specialty":"Science and Technology Studies","levelOfEducation":"Bachelors","sex":"Female","yearOfEducation":"2015","graduates":[{"firstName":"Jacob","lastName":"Battle","middleName":"Dorothy","birth":"26/10/95"},{"firstName":"Conan","lastName":"Terry","middleName":"Rama","birth":"02/08/92"},{"firstName":"Olympia","lastName":"Oliver","middleName":"Barclay","birth":"18/10/95"},{"firstName":"Ciaran","lastName":"Neal","middleName":"Thane","birth":"06/06/92"},{"firstName":"Gretchen","lastName":"Ross","middleName":"Kay","birth":"29/11/95"},{"firstName":"Emi","lastName":"Mcneil","middleName":"Mariam","birth":"19/04/91"},{"firstName":"Benjamin","lastName":"Shannon","middleName":"Camille","birth":"11/06/93"},{"firstName":"Lilah","lastName":"Mcdonald","middleName":"Merrill","birth":"19/04/90"},{"firstName":"Zahir","lastName":"Hensley","middleName":"Patience","birth":"14/05/90"},{"firstName":"Shelley","lastName":"Freeman","middleName":"Edan","birth":"02/02/89"},{"firstName":"Orlando","lastName":"Russell","middleName":"Bruno","birth":"22/05/92"},{"firstName":"Wayne","lastName":"Walsh","middleName":"Breanna","birth":"19/02/92"},{"firstName":"Kim","lastName":"Chan","middleName":"Jack","birth":"07/03/92"},{"firstName":"Kennedy","lastName":"Alston","middleName":"Miranda","birth":"15/10/95"},{"firstName":"Cedric","lastName":"Bentley","middleName":"Kenyon","birth":"19/06/95"},{"firstName":"Basia","lastName":"Hobbs","middleName":"Bernard","birth":"08/04/92"},{"firstName":"Shelley","lastName":"Bell","middleName":"Silas","birth":"16/01/93"},{"firstName":"Joy","lastName":"Daniels","middleName":"Moses","birth":"11/07/92"},{"firstName":"India","lastName":"Aguirre","middleName":"Brian","birth":"01/04/95"},{"firstName":"Mohammad","lastName":"Gay","middleName":"Myles","birth":"05/12/92"},{"firstName":"Duncan","lastName":"Bean","middleName":"Shelley","birth":"27/06/90"},{"firstName":"Shoshana","lastName":"Crosby","middleName":"Elliott","birth":"14/02/94"},{"firstName":"Vincent","lastName":"Barlow","middleName":"Galvin","birth":"21/10/90"},{"firstName":"Lev","lastName":"Wheeler","middleName":"Roth","birth":"14/08/93"},{"firstName":"Fletcher","lastName":"Clay","middleName":"May","birth":"18/02/89"},{"firstName":"Lee","lastName":"Pate","middleName":"Boris","birth":"05/09/91"},{"firstName":"Bree","lastName":"Merrill","middleName":"Remedios","birth":"16/10/95"},{"firstName":"Norman","lastName":"Mercado","middleName":"Burke","birth":"29/01/91"},{"firstName":"Jamalia","lastName":"Boyer","middleName":"Alfreda","birth":"20/03/93"},{"firstName":"Ahmed","lastName":"Moran","middleName":"Benjamin","birth":"14/09/89"},{"firstName":"Whilemina","lastName":"Holloway","middleName":"Macaulay","birth":"13/05/91"},{"firstName":"Scarlett","lastName":"Hopper","middleName":"Rose","birth":"01/06/92"}]}
