{"packageUniqueID":"ATHENS_Electrical Engineering_Masters_Male_2016","universityCode":"ATHENS","specialty":"Electrical Engineering","levelOfEducation":"Masters","sex":"Male","yearOfEducation":"2016","graduates":[{"firstName":"Callum","lastName":"Burke","middleName":"Felicia","birth":"13/10/94"},{"firstName":"Delilah","lastName":"Shepherd","middleName":"Kennan","birth":"30/03/89"},{"firstName":"Oliver","lastName":"Weber","middleName":"Ursula","birth":"25/08/94"},{"firstName":"Drew","lastName":"Dennis","middleName":"Hayden","birth":"18/07/89"},{"firstName":"Donna","lastName":"Hall","middleName":"Malcolm","birth":"09/01/94"},{"firstName":"Giselle","lastName":"Walters","middleName":"Dale","birth":"18/04/94"},{"firstName":"Tatiana","lastName":"Thornton","middleName":"Briar","birth":"13/05/91"},{"firstName":"Jescie","lastName":"Valentine","middleName":"Jesse","birth":"15/12/90"},{"firstName":"Dacey","lastName":"Lott","middleName":"Gail","birth":"04/06/90"}]}
